{
    "app_eui": "6081F9687EB91108",
    "dc": {
        "balance": 1893620,
        "nonce": 3
    },
    "decoded": {
        "payload": {
            "accuracy": 2.5,
            "altitude": 0,
            "battery": 4.02,
            "humidity": 0,
            "last_latitude": 48.97583597754456,
            "last_location": "48.97583597754456, 2.859159878442256",
            "last_longitude": 2.859159878442256,
            "minutes_lost": 166,
            "pressure": 1829,
            "sats": 0,
            "speed": 0,
            "status": "LOST GPS",
            "temperature": 6.34,
            "uptime": 356,
            "uv": 0
        },
        "status": "success"
    },
    "dev_eui": "6081F91F0E7EAD88",
    "devaddr": "21010048",
    "downlink_url": "https://console.helium.com/api/v1/down/3e7bdd5a-ae74-440d-8e14-296d96e02721/lou7K8knREIIC6XYjpWeGIkwzQPY4bj_/f49b6a32-1d4c-4b0a-b08c-405826f629d4",
    "fcnt": 712,
    "hotspots": [
        {
            "channel": 5,
            "frequency": 868.0999755859375,
            "hold_time": 0,
            "id": "11moECrYL8NpCqjTML7DEWbP8F2GRKMYEKZVgb7cM8KzTmutGRx",
            "lat": 48.86543331564107,
            "long": 2.450091466890963,
            "name": "bright-lava-condor",
            "reported_at": 1664289627297,
            "rssi": -116.0,
            "snr": -6.5,
            "spreading": "SF7BW125",
            "status": "success"
        },
        {
            "channel": 5,
            "frequency": 868.0999755859375,
            "hold_time": 0,
            "id": "11sUESQtK56mZnfWb8g13g2ZooazJTq3M8hbUPG6YwdiQwy6Ddd",
            "lat": 48.879438635758696,
            "long": 2.484844403865098,
            "name": "shaggy-frost-otter",
            "reported_at": 1664289627326,
            "rssi": -122.0,
            "snr": -6.800000190734863,
            "spreading": "SF7BW125",
            "status": "success"
        },
        {
            "channel": 5,
            "frequency": 868.0999755859375,
            "hold_time": 0,
            "id": "11yA8hAYYMTXir1inC3DDJ2efRHhsV4LR5qdP8ExWKVHS3dJdZ",
            "lat": 48.37018765070383,
            "long": 2.4957676369010042,
            "name": "active-iris-finch",
            "reported_at": 1664289627329,
            "rssi": -125.0,
            "snr": -8.5,
            "spreading": "SF7BW125",
            "status": "success"
        },
        {
            "channel": 5,
            "frequency": 868.0999755859375,
            "hold_time": 0,
            "id": "112JKWT1JtADVDjBe1u4J6fhn6t4u82pAJtS3A9pnMsoeG9CQhZD",
            "lat": 48.653664807693104,
            "long": 2.3668700757173706,
            "name": "handsome-aqua-python",
            "reported_at": 1664289627336,
            "rssi": -126.0,
            "snr": -9.800000190734863,
            "spreading": "SF7BW125",
            "status": "success"
        },
        {
            "channel": 5,
            "frequency": 868.0999755859375,
            "hold_time": 0,
            "id": "11a6rDoxve1ZakRamPeL3PPJR9rwij3QWmLpzwKo9JndJu3zyiS",
            "lat": 50.18536718152031,
            "long": 8.70173205557657,
            "name": "festive-pink-stork",
            "reported_at": 1664289627338,
            "rssi": -116.0,
            "snr": -8.199999809265137,
            "spreading": "SF7BW125",
            "status": "success"
        },
        {
            "channel": 5,
            "frequency": 868.0999755859375,
            "hold_time": 0,
            "id": "11CnnoyXTBXGz5qjvQFxKBNMvJ95FvEHTjKkgXXRhUsBcSSJumL",
            "lat": 48.08886779737706,
            "long": 3.3011624430905693,
            "name": "quaint-midnight-lynx",
            "reported_at": 1664289627338,
            "rssi": -123.0,
            "snr": -6.5,
            "spreading": "SF7BW125",
            "status": "success"
        },
        {
            "channel": 5,
            "frequency": 868.0999755859375,
            "hold_time": 0,
            "id": "11mW1W4pNQYgPMMffWnRoz9ubcCrpNjpBCvi4f3VLiLnrGvSy6x",
            "lat": 49.125112989385286,
            "long": 8.340972136046119,
            "name": "gigantic-basil-capybara",
            "reported_at": 1664289627339,
            "rssi": -109.0,
            "snr": -4.199999809265137,
            "spreading": "SF7BW125",
            "status": "success"
        },
        {
            "channel": 5,
            "frequency": 868.0999755859375,
            "hold_time": 0,
            "id": "112FeRm1ra5PxUE6CR2D2baeHEHYiQGgjHoj5xpuoGKQXrtKgrkk",
            "lat": 49.29918656595522,
            "long": 6.8093672506853435,
            "name": "interesting-mustard-antelope",
            "reported_at": 1664289627340,
            "rssi": -122.0,
            "snr": -5.5,
            "spreading": "SF7BW125",
            "status": "success"
        },
        {
            "channel": 5,
            "frequency": 868.0999755859375,
            "hold_time": 0,
            "id": "11BuQNJKp8T8PoViPUpf2WZh9PgCMAzyUmorP544AurEJDAvKHF",
            "lat": 47.876934205665314,
            "long": 7.733668772446331,
            "name": "formal-heather-aphid",
            "reported_at": 1664289627340,
            "rssi": -125.0,
            "snr": -9.199999809265137,
            "spreading": "SF7BW125",
            "status": "success"
        },
        {
            "channel": 5,
            "frequency": 868.0999755859375,
            "hold_time": 1,
            "id": "11uRzQ9JQqhy62Qkg7zTmvFk2RoXssLhaQpUtz7tfg625DZYGQD",
            "lat": 49.257369358506885,
            "long": 2.8538629409145546,
            "name": "powerful-bubblegum-gorilla",
            "reported_at": 1664289627342,
            "rssi": -126.0,
            "snr": -8.800000190734863,
            "spreading": "SF7BW125",
            "status": "success"
        },
        {
            "channel": 5,
            "frequency": 868.0999755859375,
            "hold_time": 0,
            "id": "11usaa5rMaR2Gknwkwg3goeBGRBGsKLhJc6VLE4YiG9uF9ENjc7",
            "lat": 48.370870648268614,
            "long": 2.8066570503136146,
            "name": "macho-gauze-woodpecker",
            "reported_at": 1664289627345,
            "rssi": -119.0,
            "snr": -7.800000190734863,
            "spreading": "SF7BW125",
            "status": "success"
        },
        {
            "channel": 5,
            "frequency": 868.0999755859375,
            "hold_time": 0,
            "id": "11HrNgQo69EWpJ1s8MpfD3myxcFfp2VFkGwEzCcmKvTpjHi49c4",
            "lat": 47.36928188224602,
            "long": 0.690505727934804,
            "name": "powerful-marigold-bull",
            "reported_at": 1664289627346,
            "rssi": -125.0,
            "snr": -8.5,
            "spreading": "SF7BW125",
            "status": "success"
        },
        {
            "channel": 5,
            "frequency": 868.0999755859375,
            "hold_time": 0,
            "id": "11E5zLtHMwwFAKoRrGmLz4v5ceRRacEyVqW2eER3cDPT2WHZr2N",
            "lat": 50.89384132500411,
            "long": 4.316250268512981,
            "name": "chilly-fern-horse",
            "reported_at": 1664289627346,
            "rssi": -125.0,
            "snr": -8.0,
            "spreading": "SF7BW125",
            "status": "success"
        },
        {
            "channel": 5,
            "frequency": 868.0999755859375,
            "hold_time": 0,
            "id": "112u3zdrfcqixCPH11T9FT1G4pGXd5BRNtfuBkaVsmWqaNPyCzqS",
            "lat": 50.13121066493807,
            "long": 8.756768354500274,
            "name": "massive-gunmetal-python",
            "reported_at": 1664289627346,
            "rssi": -111.0,
            "snr": -4.5,
            "spreading": "SF7BW125",
            "status": "success"
        },
        {
            "channel": 5,
            "frequency": 868.0999755859375,
            "hold_time": 0,
            "id": "112jkNwnzYvnNKskZeuTBM2oUYd9fL6cwb6J432UuorUrwYQeKjU",
            "lat": 50.13623276487847,
            "long": 8.765340776663786,
            "name": "sunny-topaz-raven",
            "reported_at": 1664289627347,
            "rssi": -115.0,
            "snr": -7.199999809265137,
            "spreading": "SF7BW125",
            "status": "success"
        },
        {
            "channel": 5,
            "frequency": 868.0999755859375,
            "hold_time": 0,
            "id": "112hUwLPcmVhdoK839CyxCkWeWzandEQSoqWcQvWAn4oSm45aEfd",
            "lat": 48.24029628170425,
            "long": 4.075005813166701,
            "name": "fun-amber-alpaca",
            "reported_at": 1664289627350,
            "rssi": -118.0,
            "snr": -2.0,
            "spreading": "SF7BW125",
            "status": "success"
        },
        {
            "channel": 5,
            "frequency": 868.0999755859375,
            "hold_time": 0,
            "id": "11mXNUvKJwJFGoZnPTB3JvGofnuxhYRaBb4XCanKXFt4ytGrfzE",
            "lat": 48.88866253226883,
            "long": 2.135347753611639,
            "name": "ancient-chambray-rabbit",
            "reported_at": 1664289627351,
            "rssi": -120.0,
            "snr": -8.0,
            "spreading": "SF7BW125",
            "status": "success"
        },
        {
            "channel": 5,
            "frequency": 868.0999755859375,
            "hold_time": 0,
            "id": "11Go7NaYo2WHfFDAMYU1hHxjmDEjpg2vhwp3JdeqDksSTSVmSkF",
            "lat": 49.192142812204644,
            "long": 5.913451896620319,
            "name": "dapper-pearl-tiger",
            "reported_at": 1664289627351,
            "rssi": -122.0,
            "snr": -4.199999809265137,
            "spreading": "SF7BW125",
            "status": "success"
        },
        {
            "channel": 5,
            "frequency": 868.0999755859375,
            "hold_time": 0,
            "id": "112kT2X98uNoiNk7T77i8HNc5xGspVa62ijxwzhtvEiZufRo3LRi",
            "lat": 48.478242437226,
            "long": 9.256985415095905,
            "name": "fantastic-goldenrod-hare",
            "reported_at": 1664289627351,
            "rssi": -125.0,
            "snr": -9.199999809265137,
            "spreading": "SF7BW125",
            "status": "success"
        },
        {
            "channel": 5,
            "frequency": 868.0999755859375,
            "hold_time": 0,
            "id": "11wD59Wn2JRQTnURmgVLTswo11gawF4AVboSbJBpQvoDsbXeMdH",
            "lat": 51.778775451149414,
            "long": 1.1290708171985355,
            "name": "magic-mint-monkey",
            "reported_at": 1664289627352,
            "rssi": -127.0,
            "snr": -7.800000190734863,
            "spreading": "SF7BW125",
            "status": "success"
        },
        {
            "channel": 5,
            "frequency": 868.0999755859375,
            "hold_time": 0,
            "id": "112fZiDAh74QvWQBTbZFJuawkVUpsBBjdwpgXxgp84UqHFZ3pqCR",
            "lat": 48.092557301996834,
            "long": 3.2949359956812234,
            "name": "polite-juniper-hedgehog",
            "reported_at": 1664289627352,
            "rssi": -121.0,
            "snr": -4.800000190734863,
            "spreading": "SF7BW125",
            "status": "success"
        },
        {
            "channel": 5,
            "frequency": 868.0999755859375,
            "hold_time": 0,
            "id": "11XTWKbLEcsnvyPCge9etim2UYfAuXjMBZoh1ZWqXHGYS3YfH4T",
            "lat": 48.13248721556313,
            "long": 4.790234125432833,
            "name": "fluffy-nylon-kookaburra",
            "reported_at": 1664289627352,
            "rssi": -119.0,
            "snr": -5.0,
            "spreading": "SF7BW125",
            "status": "success"
        },
        {
            "channel": 0,
            "frequency": 868.0999755859375,
            "hold_time": 0,
            "id": "11b6zw4FJKfLdFxYFyFpVHHoVV6Wbmf22oc6AB4NEy3cp15cWWR",
            "lat": "unknown",
            "long": "unknown",
            "name": "brisk-corduroy-raven",
            "reported_at": 1664289627352,
            "rssi": -118.0,
            "snr": 0.800000011920929,
            "spreading": "SF7BW125",
            "status": "success"
        },
        {
            "channel": 5,
            "frequency": 868.0999755859375,
            "hold_time": 0,
            "id": "112tkYu476s7XXGWKiszmLoRTNcd6mU3vFCwzaZ4hNwrU7sVkGLX",
            "lat": 52.69055671815932,
            "long": 5.007519974802297,
            "name": "tall-canvas-wren",
            "reported_at": 1664289627352,
            "rssi": -119.0,
            "snr": -9.5,
            "spreading": "SF7BW125",
            "status": "success"
        },
        {
            "channel": 5,
            "frequency": 868.0999755859375,
            "hold_time": 0,
            "id": "1128PeAZVDhLZFgFmKKLvJDLrwnaW1vge7wXCyNzgRH5EnnWqJTP",
            "lat": 49.17562410912662,
            "long": 8.6420559996137,
            "name": "special-opal-mammoth",
            "reported_at": 1664289627353,
            "rssi": -118.0,
            "snr": -4.800000190734863,
            "spreading": "SF7BW125",
            "status": "success"
        },
        {
            "channel": 5,
            "frequency": 868.0999755859375,
            "hold_time": 0,
            "id": "11215E8b2qrCRAf33nh88feqY4jGgASmFaVqZcDeXPtyzjdGSKBE",
            "lat": 47.51941345283524,
            "long": 8.24457340019631,
            "name": "suave-lipstick-crocodile",
            "reported_at": 1664289627354,
            "rssi": -125.0,
            "snr": -8.0,
            "spreading": "SF7BW125",
            "status": "success"
        },
        {
            "channel": 5,
            "frequency": 868.0999755859375,
            "hold_time": 0,
            "id": "112PteZ7zyjsomYeWZzaDdFDwgQ5iTxkUNT8BiwCbSCmHXQbW2H9",
            "lat": 51.081548442918475,
            "long": 5.260348551474474,
            "name": "funny-viridian-leopard",
            "reported_at": 1664289627355,
            "rssi": -116.0,
            "snr": -6.800000190734863,
            "spreading": "SF7BW125",
            "status": "success"
        },
        {
            "channel": 5,
            "frequency": 868.0999755859375,
            "hold_time": 0,
            "id": "11NDUAPC3u5Y8yAVuJL1Q9swdbMbMb6jZwHpzWq5zhekAsEWG3E",
            "lat": 45.737590803629345,
            "long": 3.211650292266381,
            "name": "round-licorice-millipede",
            "reported_at": 1664289627356,
            "rssi": -127.0,
            "snr": -9.800000190734863,
            "spreading": "SF7BW125",
            "status": "success"
        },
        {
            "channel": 5,
            "frequency": 868.0999755859375,
            "hold_time": 0,
            "id": "11pDxoqZPFBcZ7KMDLyXJfseKRzAWmBiTz3YVGMSLh1Lzk3NHr1",
            "lat": 48.697952864654326,
            "long": 6.173088167018993,
            "name": "happy-cinnamon-ladybug",
            "reported_at": 1664289627357,
            "rssi": -119.0,
            "snr": -4.199999809265137,
            "spreading": "SF7BW125",
            "status": "success"
        },
        {
            "channel": 5,
            "frequency": 868.0999755859375,
            "hold_time": 0,
            "id": "11Mzh2oQchFRwCCE6rLN1Sm4drDSmYdntNeVQo1pGHV35ALPkYU",
            "lat": 51.296248519424886,
            "long": 3.1141178684822943,
            "name": "magnificent-menthol-penguin",
            "reported_at": 1664289627357,
            "rssi": -125.0,
            "snr": -9.0,
            "spreading": "SF7BW125",
            "status": "success"
        },
        {
            "channel": 5,
            "frequency": 868.0999755859375,
            "hold_time": 1,
            "id": "112ciFjmYDR6fVpd3AbSCVRtr8neSidjyn8L35uZpG3XmFVJSa7b",
            "lat": 48.23198987435836,
            "long": 4.115068764364667,
            "name": "square-cherry-sardine",
            "reported_at": 1664289627357,
            "rssi": -124.0,
            "snr": -9.5,
            "spreading": "SF7BW125",
            "status": "success"
        },
        {
            "channel": 5,
            "frequency": 868.0999755859375,
            "hold_time": 0,
            "id": "112wDfw2GYixuxzivkDL7fqGFznwSXG2xakBWi8f83bLectLAQUc",
            "lat": 52.690972330388654,
            "long": 5.0050707044236535,
            "name": "amateur-daisy-flamingo",
            "reported_at": 1664289627358,
            "rssi": -121.0,
            "snr": -9.5,
            "spreading": "SF7BW125",
            "status": "success"
        },
        {
            "channel": 5,
            "frequency": 868.0999755859375,
            "hold_time": 0,
            "id": "112Vp4wTXBQ2WZQGabqigit56c1LKJHhmp1Rc19GDPNPevz9P36B",
            "lat": 48.62061466333537,
            "long": 6.109220675217716,
            "name": "wild-mint-chimpanzee",
            "reported_at": 1664289627361,
            "rssi": -119.0,
            "snr": -6.5,
            "spreading": "SF7BW125",
            "status": "success"
        },
        {
            "channel": 5,
            "frequency": 868.0999755859375,
            "hold_time": 0,
            "id": "112PeWcFoJLss1juv7YLoeQZdkrWUgNrDtHXU66wdKUZhYPZSx77",
            "lat": 51.03042639614764,
            "long": 3.8435750395823503,
            "name": "creamy-concrete-python",
            "reported_at": 1664289627362,
            "rssi": -126.0,
            "snr": -8.5,
            "spreading": "SF7BW125",
            "status": "success"
        },
        {
            "channel": 5,
            "frequency": 868.0999755859375,
            "hold_time": 0,
            "id": "11h6LHGLGYUtZVF2ZT3dAu9WPeST1V5foXgSaxrqMhAcXxUJrjL",
            "lat": 48.284484117188406,
            "long": 4.065296142856956,
            "name": "cool-chambray-mantis",
            "reported_at": 1664289627362,
            "rssi": -115.0,
            "snr": 2.200000047683716,
            "spreading": "SF7BW125",
            "status": "success"
        },
        {
            "channel": 5,
            "frequency": 868.0999755859375,
            "hold_time": 0,
            "id": "11Sn7W896a81kwsk7VXrexVykncdUq8HZzKjd55D1xL9FYveTTW",
            "lat": 52.69745747753691,
            "long": 5.001893170930678,
            "name": "mammoth-chambray-iguana",
            "reported_at": 1664289627363,
            "rssi": -119.0,
            "snr": -9.199999809265137,
            "spreading": "SF7BW125",
            "status": "success"
        },
        {
            "channel": 5,
            "frequency": 868.0999755859375,
            "hold_time": 0,
            "id": "11X4hKwHET38Vpgm78cRowJ99GSAzCRtPkqkvh17cqtFrpeZzZZ",
            "lat": 49.14286301807746,
            "long": 5.884367915141917,
            "name": "beautiful-amethyst-platypus",
            "reported_at": 1664289627364,
            "rssi": -121.0,
            "snr": -3.5,
            "spreading": "SF7BW125",
            "status": "success"
        },
        {
            "channel": 5,
            "frequency": 868.0999755859375,
            "hold_time": 0,
            "id": "1129NGK5bSNCDEKnXrAZkdgx2eFySxApDKCwCj3ddPittVTcaRMB",
            "lat": 51.09970585445197,
            "long": 4.663437655637403,
            "name": "savory-blonde-giraffe",
            "reported_at": 1664289627366,
            "rssi": -127.0,
            "snr": -10.5,
            "spreading": "SF7BW125",
            "status": "success"
        },
        {
            "channel": 5,
            "frequency": 868.0999755859375,
            "hold_time": 0,
            "id": "119gGeoiEGshDBVj383BoquoHeTcXakTA99hbqjxQLebCsn4JAc",
            "lat": 49.22009619235969,
            "long": 6.85858758873091,
            "name": "nice-gingerbread-ape",
            "reported_at": 1664289627368,
            "rssi": -123.0,
            "snr": -6.800000190734863,
            "spreading": "SF7BW125",
            "status": "success"
        },
        {
            "channel": 5,
            "frequency": 868.0999755859375,
            "hold_time": 0,
            "id": "112CkuWzD59AGzKN7FL5JQFfqYr4TnsQuch2abymLEMEt5AtMUKW",
            "lat": 48.807913434051585,
            "long": 2.068391973056098,
            "name": "zany-berry-goat",
            "reported_at": 1664289627369,
            "rssi": -124.0,
            "snr": -5.5,
            "spreading": "SF7BW125",
            "status": "success"
        },
        {
            "channel": 5,
            "frequency": 868.0999755859375,
            "hold_time": 0,
            "id": "11hy9ZnAW4UyFEKoZ9nRY9Tb1YuZ3yfbbdazinFjC9M54F8CDHb",
            "lat": 49.05755283401733,
            "long": 6.05807415446965,
            "name": "micro-raisin-moth",
            "reported_at": 1664289627370,
            "rssi": -126.0,
            "snr": -9.0,
            "spreading": "SF7BW125",
            "status": "success"
        },
        {
            "channel": 5,
            "frequency": 868.0999755859375,
            "hold_time": 0,
            "id": "112kL1qGZ6EgLe2kTaGF8iW8m1AJ5gMaysAwTiYjZBCum2wMvsxG",
            "lat": 49.586730768824346,
            "long": 6.102317913930776,
            "name": "sharp-cotton-bobcat",
            "reported_at": 1664289627371,
            "rssi": -122.0,
            "snr": -4.199999809265137,
            "spreading": "SF7BW125",
            "status": "success"
        },
        {
            "channel": 5,
            "frequency": 868.0999755859375,
            "hold_time": 0,
            "id": "11vafdF69uGFr3Tid2GcQbdDkMmFCizobdb9LihNFTG3f557pi1",
            "lat": 47.17270380395117,
            "long": 8.287789268101145,
            "name": "sleepy-licorice-eel",
            "reported_at": 1664289627372,
            "rssi": -124.0,
            "snr": -7.0,
            "spreading": "SF7BW125",
            "status": "success"
        },
        {
            "channel": 5,
            "frequency": 868.0999755859375,
            "hold_time": 0,
            "id": "11MW1XBPiEoWqjVxynT5N3ntjjF4tmh6NfCcubdYtzyJyzf4AJD",
            "lat": 50.667517459455176,
            "long": 7.1788000094091515,
            "name": "interesting-mahogany-dog",
            "reported_at": 1664289627373,
            "rssi": -127.0,
            "snr": -9.199999809265137,
            "spreading": "SF7BW125",
            "status": "success"
        },
        {
            "channel": 5,
            "frequency": 868.0999755859375,
            "hold_time": 0,
            "id": "11HMZ6NKUrYFLkc3aSdbgExz3mUrZ3tpqfWKDbr2iUxiBewk2Cj",
            "lat": 48.88487451295649,
            "long": 2.350319617917227,
            "name": "spicy-hazel-bee",
            "reported_at": 1664289627373,
            "rssi": -124.0,
            "snr": -5.199999809265137,
            "spreading": "SF7BW125",
            "status": "success"
        },
        {
            "channel": 5,
            "frequency": 868.0999755859375,
            "hold_time": 0,
            "id": "112YVP5tbJVzczoqoQPFBSMjkwSNgooahiR7MkUJGt7Go5bxC9KH",
            "lat": 51.30404897415627,
            "long": 3.094063674546119,
            "name": "damaged-peach-rook",
            "reported_at": 1664289627374,
            "rssi": -123.0,
            "snr": -7.800000190734863,
            "spreading": "SF7BW125",
            "status": "success"
        },
        {
            "channel": 5,
            "frequency": 868.0999755859375,
            "hold_time": 0,
            "id": "1183g8ou78Mvd2cK2vYQ87XgQsF6dBzBQZUax7PLvy7hgHyAVJp",
            "lat": 49.47231796194834,
            "long": 8.209834234230366,
            "name": "smooth-green-bobcat",
            "reported_at": 1664289627374,
            "rssi": -126.0,
            "snr": -7.199999809265137,
            "spreading": "SF7BW125",
            "status": "success"
        },
        {
            "channel": 5,
            "frequency": 868.0999755859375,
            "hold_time": 0,
            "id": "112PAZmzb6V8uQdvdpXMQYnyzEUZMbbBaKj346e3L7wE1CEWdXck",
            "lat": 51.107415552014494,
            "long": 6.817192090679785,
            "name": "smooth-eggshell-unicorn",
            "reported_at": 1664289627374,
            "rssi": -124.0,
            "snr": -7.199999809265137,
            "spreading": "SF7BW125",
            "status": "success"
        },
        {
            "channel": 5,
            "frequency": 868.0999755859375,
            "hold_time": 0,
            "id": "11PMFsPWyLvDBYGeUUnW817ZhMHzk2Fjt6MHHamq8JHTitQjqFC",
            "lat": 49.52571816074861,
            "long": 6.866449225781651,
            "name": "melodic-golden-dalmatian",
            "reported_at": 1664289627375,
            "rssi": -124.0,
            "snr": -8.199999809265137,
            "spreading": "SF7BW125",
            "status": "success"
        },
        {
            "channel": 5,
            "frequency": 868.0999755859375,
            "hold_time": 0,
            "id": "11aVkBRaT5XCM4ngVwVir5HgrHd6JbaNqiXHi82HdYC3m5yBthw",
            "lat": 49.895328198387034,
            "long": 8.689061383688143,
            "name": "furry-laurel-loris",
            "reported_at": 1664289627377,
            "rssi": -122.0,
            "snr": -5.0,
            "spreading": "SF7BW125",
            "status": "success"
        },
        {
            "channel": 5,
            "frequency": 868.0999755859375,
            "hold_time": 0,
            "id": "11DoZ8C3HL9c2VXfsqD4mktNUr6WvjPwfBVGMipozzTcPDAGHYP",
            "lat": 49.600614597567585,
            "long": 6.091173064036938,
            "name": "amateur-seaweed-bull",
            "reported_at": 1664289627378,
            "rssi": -122.0,
            "snr": -6.199999809265137,
            "spreading": "SF7BW125",
            "status": "success"
        },
        {
            "channel": 5,
            "frequency": 868.0999755859375,
            "hold_time": 0,
            "id": "1123RL59LpX3zUBwmYRMT3vhh2judnZZxJB9RPHp6GW6SMC7ECja",
            "lat": 50.964697284631825,
            "long": 5.525414169802049,
            "name": "keen-smoke-armadillo",
            "reported_at": 1664289627379,
            "rssi": -117.0,
            "snr": -7.5,
            "spreading": "SF7BW125",
            "status": "success"
        },
        {
            "channel": 5,
            "frequency": 868.0999755859375,
            "hold_time": 0,
            "id": "1128sLuUCgaqiGaQs8rVcJEq6YWR7Sncv3khAC1ZJheuRnMti6eQ",
            "lat": 49.99261414104915,
            "long": 8.023490477975841,
            "name": "damaged-brown-dove",
            "reported_at": 1664289627379,
            "rssi": -126.0,
            "snr": -9.0,
            "spreading": "SF7BW125",
            "status": "success"
        },
        {
            "channel": 5,
            "frequency": 868.0999755859375,
            "hold_time": 0,
            "id": "112qQnpCkpvw17nhaTuo6SszMMtA53LvcrBp5JjUxjwHKmNddmS9",
            "lat": 49.866770350417205,
            "long": 8.926236998426969,
            "name": "modern-concrete-bat",
            "reported_at": 1664289627380,
            "rssi": -125.0,
            "snr": -7.5,
            "spreading": "SF7BW125",
            "status": "success"
        },
        {
            "channel": 5,
            "frequency": 868.0999755859375,
            "hold_time": 0,
            "id": "11bye82NcqnmWcEt3rwq8rgNUsgoeECGUaM84pG1EmUkbMbuKgX",
            "lat": 48.55931810499309,
            "long": 7.783064566653979,
            "name": "blurry-chambray-canary",
            "reported_at": 1664289627380,
            "rssi": -124.0,
            "snr": -7.0,
            "spreading": "SF7BW125",
            "status": "success"
        },
        {
            "channel": 5,
            "frequency": 868.0999755859375,
            "hold_time": 0,
            "id": "11UyL6xRv3CHncqNq1NSfXqZgj6WXejU4T4dVn5io4HXh4fMcGS",
            "lat": 49.106808766946116,
            "long": 8.81551886791987,
            "name": "slow-pear-fox",
            "reported_at": 1664289627381,
            "rssi": -125.0,
            "snr": -7.199999809265137,
            "spreading": "SF7BW125",
            "status": "success"
        },
        {
            "channel": 5,
            "frequency": 868.0999755859375,
            "hold_time": 0,
            "id": "112guwKUWR1bKirKtorVwwveRkpmEbUqUFWbckcxiMt8yCuteNVZ",
            "lat": 49.88529996594495,
            "long": 9.161348442518843,
            "name": "electric-boysenberry-walrus",
            "reported_at": 1664289627382,
            "rssi": -116.0,
            "snr": -7.0,
            "spreading": "SF7BW125",
            "status": "success"
        },
        {
            "channel": 5,
            "frequency": 868.0999755859375,
            "hold_time": 1,
            "id": "112kvKMgJga7sxGGnmae9KEuCfAtzxL5TEDuvWcnhVxkV4xNwBBS",
            "lat": 48.28349478778845,
            "long": 3.9849465562648376,
            "name": "soaring-cloud-opossum",
            "reported_at": 1664289627382,
            "rssi": -125.0,
            "snr": -8.199999809265137,
            "spreading": "SF7BW125",
            "status": "success"
        },
        {
            "channel": 5,
            "frequency": 868.0999755859375,
            "hold_time": 0,
            "id": "1122UqqgazwUrUCnhFuY6nyNuMMjpXkPFwH22oYeeMQdVnnatgZs",
            "lat": 49.37379202325004,
            "long": 8.442373767471524,
            "name": "dazzling-ivory-cheetah",
            "reported_at": 1664289627383,
            "rssi": -126.0,
            "snr": -7.800000190734863,
            "spreading": "SF7BW125",
            "status": "success"
        },
        {
            "channel": 5,
            "frequency": 868.0999755859375,
            "hold_time": 0,
            "id": "11KJxRiX1wC3SRDQekN6fvLu5vkjiNDXjVTyqj2bnnXwNAPg2ze",
            "lat": 49.26799884836455,
            "long": 7.171091026102491,
            "name": "muscular-carbon-nightingale",
            "reported_at": 1664289627384,
            "rssi": -128.0,
            "snr": -8.5,
            "spreading": "SF7BW125",
            "status": "success"
        },
        {
            "channel": 5,
            "frequency": 868.0999755859375,
            "hold_time": 0,
            "id": "11MfNm3yZiMYKCxTam5BTpaL45S8CEp29t3utjGso6eyTJPFg8V",
            "lat": 47.43127542434406,
            "long": 8.28756036619264,
            "name": "icy-emerald-condor",
            "reported_at": 1664289627384,
            "rssi": -127.0,
            "snr": -9.5,
            "spreading": "SF7BW125",
            "status": "success"
        },
        {
            "channel": 5,
            "frequency": 868.0999755859375,
            "hold_time": 0,
            "id": "11kEhrkMc1pfdnj1Dv8gPmfNndbfUmAGfkdaZWzcAjKCXoeZ8Qp",
            "lat": 46.1229081045118,
            "long": 6.103895977579128,
            "name": "creamy-chiffon-bobcat",
            "reported_at": 1664289627385,
            "rssi": -120.0,
            "snr": -9.5,
            "spreading": "SF7BW125",
            "status": "success"
        },
        {
            "channel": 5,
            "frequency": 868.0999755859375,
            "hold_time": 0,
            "id": "11DfyZaD3eK4tJBvBcMmKhQepDsEj5SCPyhzfmxJLgBgoWr9oVV",
            "lat": 51.77497514193849,
            "long": 6.112470542622189,
            "name": "delightful-zinc-puppy",
            "reported_at": 1664289627387,
            "rssi": -121.0,
            "snr": -9.5,
            "spreading": "SF7BW125",
            "status": "success"
        },
        {
            "channel": 5,
            "frequency": 868.0999755859375,
            "hold_time": 0,
            "id": "112GMtpCtY2LhdQHdbZitrpNrZ2aouKeK7ZJPKqHZrjdo3n3LntS",
            "lat": 49.63105343761633,
            "long": 8.615329633127752,
            "name": "overt-lime-lark",
            "reported_at": 1664289627390,
            "rssi": -114.0,
            "snr": -5.0,
            "spreading": "SF7BW125",
            "status": "success"
        },
        {
            "channel": 5,
            "frequency": 868.0999755859375,
            "hold_time": 0,
            "id": "11TD3pfENq1SKFvtsJzo2WGpeTPMV9ayt61yAgifwRijWpwECLv",
            "lat": 51.10184413079207,
            "long": 5.8187244174792605,
            "name": "long-ceramic-jay",
            "reported_at": 1664289627390,
            "rssi": -128.0,
            "snr": -10.0,
            "spreading": "SF7BW125",
            "status": "success"
        },
        {
            "channel": 5,
            "frequency": 868.0999755859375,
            "hold_time": 0,
            "id": "11BgMfheyR3TCXRahGxeZN1HrRRakoeXxp6jMAse67zM6ziC2DK",
            "lat": 49.64141157425996,
            "long": 8.610063818003,
            "name": "icy-umber-narwhal",
            "reported_at": 1664289627390,
            "rssi": -110.0,
            "snr": -7.800000190734863,
            "spreading": "SF7BW125",
            "status": "success"
        },
        {
            "channel": 5,
            "frequency": 868.0999755859375,
            "hold_time": 0,
            "id": "118hE2ioWCtpT7jkXseiB7rmd2SYT3VbudUjZiGD53jsdx17ei7",
            "lat": 49.644685931783556,
            "long": 8.624566125275235,
            "name": "rough-iron-huskie",
            "reported_at": 1664289627391,
            "rssi": -110.0,
            "snr": -8.0,
            "spreading": "SF7BW125",
            "status": "success"
        },
        {
            "channel": 5,
            "frequency": 868.0999755859375,
            "hold_time": 0,
            "id": "112KdBRCqzfbYujVMupDECWJtxHe3BiVBVMpSvUUse2k1Sq6wUXd",
            "lat": 49.59753378900235,
            "long": 6.086149157684161,
            "name": "unique-mahogany-seahorse",
            "reported_at": 1664289627391,
            "rssi": -118.0,
            "snr": -5.800000190734863,
            "spreading": "SF7BW125",
            "status": "success"
        },
        {
            "channel": 5,
            "frequency": 868.0999755859375,
            "hold_time": 0,
            "id": "11XnbcSNp9nJHxdHcxkoTSWidrbkM7GK8Fzg2mquMManKaGJWiR",
            "lat": 51.017586217447096,
            "long": 5.335144995589006,
            "name": "swift-ash-snail",
            "reported_at": 1664289627392,
            "rssi": -125.0,
            "snr": -8.199999809265137,
            "spreading": "SF7BW125",
            "status": "success"
        },
        {
            "channel": 5,
            "frequency": 868.0999755859375,
            "hold_time": 0,
            "id": "11eM1dQcwGzAuMw2XSZY2VoR3FD7cytcCTK3LHbmJYKdjfSVrab",
            "lat": 49.379941847896966,
            "long": 7.356122522384008,
            "name": "oblong-emerald-rattlesnake",
            "reported_at": 1664289627393,
            "rssi": -116.0,
            "snr": -8.0,
            "spreading": "SF7BW125",
            "status": "success"
        },
        {
            "channel": 5,
            "frequency": 868.0999755859375,
            "hold_time": 0,
            "id": "11BUdatdyHPsf2EQiCWgFGf6ZHQ1kLwGutWcpaBjVtGzt51Fcd6",
            "lat": 49.35979819838384,
            "long": 7.100376182410035,
            "name": "plain-cyan-wolverine",
            "reported_at": 1664289627393,
            "rssi": -128.0,
            "snr": -7.0,
            "spreading": "SF7BW125",
            "status": "success"
        },
        {
            "channel": 5,
            "frequency": 868.0999755859375,
            "hold_time": 0,
            "id": "112dyfVFALe8iVs6b9UA2ADgXNkuJqR2wgMS2BbUusJ4ofCtw6VV",
            "lat": 48.032880056137685,
            "long": 7.7619570731354814,
            "name": "amateur-coffee-cow",
            "reported_at": 1664289627400,
            "rssi": -123.0,
            "snr": -7.199999809265137,
            "spreading": "SF7BW125",
            "status": "success"
        },
        {
            "channel": 5,
            "frequency": 868.0999755859375,
            "hold_time": 0,
            "id": "112KxnzuUfb8pn3jdoRZ5R38JE9vZjtiLxCi7tJpqKpuM9MFAaoN",
            "lat": 49.63832984748043,
            "long": 8.621618908570428,
            "name": "scrawny-arctic-octopus",
            "reported_at": 1664289627415,
            "rssi": -108.0,
            "snr": -8.0,
            "spreading": "SF7BW125",
            "status": "success"
        },
        {
            "channel": 5,
            "frequency": 868.0999755859375,
            "hold_time": 0,
            "id": "112LouJ9hjgG7rSVp344jXyHYSjQFshqeCPV7gHi2r78SsnGmG5T",
            "lat": 49.638834610012864,
            "long": 8.638109284004306,
            "name": "curved-orchid-bird",
            "reported_at": 1664289627419,
            "rssi": -117.0,
            "snr": -5.0,
            "spreading": "SF7BW125",
            "status": "success"
        },
        {
            "channel": 5,
            "frequency": 868.0999755859375,
            "hold_time": 55,
            "id": "11J4jE4iSHa5vCZm8uDgsUKYBcFAWHTEvzKgMGZNy8gx7TjcBNF",
            "lat": 46.248145037389726,
            "long": 6.229588281737184,
            "name": "stale-brick-halibut",
            "reported_at": 1664289627419,
            "rssi": -123.0,
            "snr": -9.199999809265137,
            "spreading": "SF7BW125",
            "status": "success"
        },
        {
            "channel": 5,
            "frequency": 868.0999755859375,
            "hold_time": 0,
            "id": "11oGGkm3XTibFUirH2Fsgxp4eZwV6RAbsKZVMhck5JhgyeWRnq2",
            "lat": 48.96384256230953,
            "long": 2.5305672111104536,
            "name": "late-pineapple-panther",
            "reported_at": 1664289627424,
            "rssi": -114.0,
            "snr": -7.0,
            "spreading": "SF7BW125",
            "status": "success"
        },
        {
            "channel": 5,
            "frequency": 868.0999755859375,
            "hold_time": 0,
            "id": "1127r5BfoMUex7MGnscm1kNn7Pokduf8HknKZX4udsAYCzq5pp9k",
            "lat": 49.74950242946144,
            "long": 7.118160181193281,
            "name": "massive-opal-osprey",
            "reported_at": 1664289627431,
            "rssi": -125.0,
            "snr": -6.800000190734863,
            "spreading": "SF7BW125",
            "status": "success"
        },
        {
            "channel": 5,
            "frequency": 868.0999755859375,
            "hold_time": 0,
            "id": "112mjBw6dNVjXUxkWGMZb1Mp34GLw5VLYXcyhiWjrAN8QZkZzN43",
            "lat": 49.000124698081734,
            "long": 2.2573844322125973,
            "name": "quiet-pickle-sloth",
            "reported_at": 1664289627435,
            "rssi": -125.0,
            "snr": -8.800000190734863,
            "spreading": "SF7BW125",
            "status": "success"
        },
        {
            "channel": 5,
            "frequency": 868.0999755859375,
            "hold_time": 0,
            "id": "118H7k7CsV1AF8EWHFEgPobB6idXDmtgqwJizPbCVeBWPDmsVA8",
            "lat": 49.17859864373898,
            "long": 8.647481728930972,
            "name": "stale-mustard-goose",
            "reported_at": 1664289627443,
            "rssi": -114.0,
            "snr": -4.199999809265137,
            "spreading": "SF7BW125",
            "status": "success"
        },
        {
            "channel": 5,
            "frequency": 868.0999755859375,
            "hold_time": 0,
            "id": "114VbeH1YuSeRBVsgEWJPRyhaAsKsVEFum2KQYodUoCYuokZ8NX",
            "lat": 49.54282660223395,
            "long": 6.13707277802073,
            "name": "harsh-candy-chipmunk",
            "reported_at": 1664289627447,
            "rssi": -123.0,
            "snr": -5.0,
            "spreading": "SF7BW125",
            "status": "success"
        },
        {
            "channel": 5,
            "frequency": 868.0999755859375,
            "hold_time": 0,
            "id": "11RNQHvMokBDpoxYdLjELYkAxgF1bHd8ANycgvEuPmY9E8f7D9Y",
            "lat": 48.56247566379867,
            "long": 9.122031169718355,
            "name": "gorgeous-bronze-salamander",
            "reported_at": 1664289627597,
            "rssi": -121.0,
            "snr": -8.0,
            "spreading": "SF7BW125",
            "status": "success"
        },
        {
            "channel": 5,
            "frequency": 868.0999755859375,
            "hold_time": 0,
            "id": "11oMY76yHdbf7iARMUwxPRZAajAaBQRBku8R3g73YcGZpQhZ2JN",
            "lat": 48.58790026098264,
            "long": 9.138861862095137,
            "name": "clumsy-coal-goat",
            "reported_at": 1664289627599,
            "rssi": -118.0,
            "snr": -8.0,
            "spreading": "SF7BW125",
            "status": "success"
        },
        {
            "channel": 5,
            "frequency": 868.0999755859375,
            "hold_time": 0,
            "id": "1127DgjUdgKzBb8WxkSjKShGkTyrpUz3Q5w36FPhSwTzBghQ8hXL",
            "lat": 47.44438202132974,
            "long": 8.35608231001117,
            "name": "dancing-aqua-corgi",
            "reported_at": 1664289627610,
            "rssi": -113.0,
            "snr": -10.0,
            "spreading": "SF7BW125",
            "status": "success"
        },
        {
            "channel": 5,
            "frequency": 868.0999755859375,
            "hold_time": 0,
            "id": "11cQ7KdWggRcsMpnNH4UC4YmhSj1HJZMgkG8xiCwVjGAxw6DfJ9",
            "lat": 49.58973916028715,
            "long": 6.1261240413356735,
            "name": "furry-hickory-pelican",
            "reported_at": 1664289627656,
            "rssi": -113.0,
            "snr": -6.5,
            "spreading": "SF7BW125",
            "status": "success"
        },
        {
            "channel": 5,
            "frequency": 868.0999755859375,
            "hold_time": 0,
            "id": "11suSuPkoBN6jgRq6jFQ2B4AZ5iUb5r5ibnTfNv1JMhtDosMt5m",
            "lat": 48.56634152223234,
            "long": 9.124729281440153,
            "name": "cheery-infrared-tuna",
            "reported_at": 1664289627657,
            "rssi": -123.0,
            "snr": -8.0,
            "spreading": "SF7BW125",
            "status": "success"
        }
    ],
    "id": "f49b6a32-1d4c-4b0a-b08c-405826f629d4",
    "metadata": {
        "adr_allowed": false,
        "cf_list_enabled": false,
        "labels": [
            {
                "id": "0095bae0-cf3d-448d-ab8c-a050ae632e2b",
                "name": "Tracker Label",
                "organization_id": "864fea78-44c3-40ff-bf06-37902ae7bae8"
            }
        ],
        "multi_buy": 9999,
        "organization_id": "864fea78-44c3-40ff-bf06-37902ae7bae8",
        "preferred_hotspots": [],
        "rx_delay": 1,
        "rx_delay_actual": 1,
        "rx_delay_state": "rx_delay_established"
    },
    "name": "Balloon Tracker",
    "payload": "xaeOggh+AAAAygABZACmAnoAByUAAAAA",
    "payload_size": 24,
    "port": 6,
    "raw_packet": "QCEBAEgAyAIGDEqIOcq6fyU+59NDDn13GLpdU0lwIAFqHQPSLg==",
    "replay": false,
    "reported_at": 1664289627297,
    "type": "uplink",
    "uuid": "47124e5c-69a9-4222-af3f-243ecba5df49"
}